kimi_agent_sdk/__init__.py
kimi_agent_sdk/_aggregator.py
kimi_agent_sdk/_approval.py
kimi_agent_sdk/_exception.py
kimi_agent_sdk/_prompt.py
kimi_agent_sdk/_session.py
kimi_agent_sdk/py.typed
kimi_agent_sdk-0.0.3.dist-info/WHEEL
kimi_agent_sdk-0.0.3.dist-info/METADATA
kimi_agent_sdk-0.0.3.dist-info/RECORD
