Metadata-Version: 2.3
Name: kimi-agent-sdk
Version: 0.0.3
Summary: A Python SDK for Kimi Agent (Kimi CLI).
Keywords: kimi,agent,sdk,coding-agents,llm,automation
Author: Moonshot AI
Author-email: Moonshot AI <team@moonshot.ai>
License: Apache-2.0
Classifier: Typing :: Typed
Classifier: Intended Audience :: Developers
Classifier: Programming Language :: Python :: 3
Classifier: Programming Language :: Python :: 3.12
Classifier: Programming Language :: Python :: 3.13
Classifier: Programming Language :: Python :: 3.14
Classifier: Operating System :: OS Independent
Classifier: Topic :: Software Development :: Libraries :: Python Modules
Classifier: License :: OSI Approved :: Apache Software License
Requires-Dist: kimi-cli>=0.83,<0.84
Requires-Dist: kosong>=0.39.0,<0.40.0
Requires-Python: >=3.12
Project-URL: Changelog, https://github.com/MoonshotAI/kimi-agent-sdk/blob/main/python/CHANGELOG.md
Project-URL: Documentation, https://github.com/MoonshotAI/kimi-agent-sdk/tree/main/README.md
Project-URL: Homepage, https://github.com/MoonshotAI/kimi-agent-sdk
Project-URL: Issues, https://github.com/MoonshotAI/kimi-agent-sdk/issues
Project-URL: Repository, https://github.com/MoonshotAI/kimi-agent-sdk
